odoo/addons/ssi_consulting/README.rst
odoo/addons/ssi_consulting/__init__.py
odoo/addons/ssi_consulting/__manifest__.py
odoo/addons/ssi_consulting/menu.xml
odoo/addons/ssi_consulting/approval_template/consulting_service.xml
odoo/addons/ssi_consulting/approval_template/consulting_service_business_process.xml
odoo/addons/ssi_consulting/approval_template/consulting_service_business_process_area.xml
odoo/addons/ssi_consulting/approval_template/consulting_service_document_extraction.xml
odoo/addons/ssi_consulting/approval_template/consulting_service_document_type.xml
odoo/addons/ssi_consulting/approval_template/consulting_service_entity.xml
odoo/addons/ssi_consulting/approval_template/consulting_service_issue.xml
odoo/addons/ssi_consulting/approval_template/consulting_service_materialized_view.xml
odoo/addons/ssi_consulting/data/schema_parser_category.xml
odoo/addons/ssi_consulting/i18n/ssi_consulting.pot
odoo/addons/ssi_consulting/ir_sequence/consulting_service.xml
odoo/addons/ssi_consulting/ir_sequence/consulting_service_business_process.xml
odoo/addons/ssi_consulting/ir_sequence/consulting_service_business_process_area.xml
odoo/addons/ssi_consulting/ir_sequence/consulting_service_document_extraction.xml
odoo/addons/ssi_consulting/ir_sequence/consulting_service_document_type.xml
odoo/addons/ssi_consulting/ir_sequence/consulting_service_entity.xml
odoo/addons/ssi_consulting/ir_sequence/consulting_service_issue.xml
odoo/addons/ssi_consulting/ir_sequence/consulting_service_materialized_view.xml
odoo/addons/ssi_consulting/models/__init__.py
odoo/addons/ssi_consulting/models/consulting_chart_template.py
odoo/addons/ssi_consulting/models/consulting_dashboard_template.py
odoo/addons/ssi_consulting/models/consulting_data_structure.py
odoo/addons/ssi_consulting/models/consulting_issue_template.py
odoo/addons/ssi_consulting/models/consulting_materialized_view.py
odoo/addons/ssi_consulting/models/consulting_report_template.py
odoo14_addon_ssi_consulting-14.0.5.19.0.dist-info/METADATA
odoo14_addon_ssi_consulting-14.0.5.19.0.dist-info/WHEEL
odoo14_addon_ssi_consulting-14.0.5.19.0.dist-info/top_level.txt
odoo14_addon_ssi_consulting-14.0.5.19.0.dist-info/RECORD
